warg_openapi/__init__.py
warg_openapi/api/__init__.py
warg_openapi/api/content_api.py
warg_openapi/api/fetch_api.py
warg_openapi/api/ledger_api.py
warg_openapi/api/monitor_api.py
warg_openapi/api/package_api.py
warg_openapi/api/proof_api.py
warg_openapi/api_client.py
warg_openapi/api_response.py
warg_openapi/configuration.py
warg_openapi/exceptions.py
warg_openapi/models/__init__.py
warg_openapi/models/bundle_failure_error.py
warg_openapi/models/checkpoint.py
warg_openapi/models/checkpoint_verification_response.py
warg_openapi/models/content_sources_response.py
warg_openapi/models/envelope_body.py
warg_openapi/models/error.py
warg_openapi/models/fetch_logs404_response.py
warg_openapi/models/fetch_logs_id_not_found_error.py
warg_openapi/models/fetch_logs_log_length_not_found_error.py
warg_openapi/models/fetch_logs_request.py
warg_openapi/models/fetch_logs_response.py
warg_openapi/models/fetch_names404_response.py
warg_openapi/models/fetch_package_names_request.py
warg_openapi/models/fetch_package_names_response.py
warg_openapi/models/fetch_warning.py
warg_openapi/models/get_content_sources404_response.py
warg_openapi/models/get_package_record404_response.py
warg_openapi/models/http_get.py
warg_openapi/models/http_upload.py
warg_openapi/models/http_upload_headers.py
warg_openapi/models/incorrect_proof_error.py
warg_openapi/models/ledger_sources_response.py
warg_openapi/models/ledger_sources_response_sources_inner.py
warg_openapi/models/missing_content.py
warg_openapi/models/package_not_included_error.py
warg_openapi/models/package_record.py
warg_openapi/models/processing_record.py
warg_openapi/models/prove_consistency404_response.py
warg_openapi/models/prove_consistency_request.py
warg_openapi/models/prove_consistency_response.py
warg_openapi/models/prove_inclusion404_response.py
warg_openapi/models/prove_inclusion422_response.py
warg_openapi/models/prove_inclusion_request.py
warg_openapi/models/prove_inclusion_response.py
wasm_action-0.0.6.dist-info/WHEEL
wasm_action-0.0.6.dist-info/entry_points.txt
wasm_action-0.0.6.dist-info/METADATA
wasm_action-0.0.6.dist-info/RECORD
