Metadata-Version: 2.3
Name: wasm-action
Version: 0.0.6
Summary: Interact with WebAssembly registries.
Requires-Dist: click>=8.2.1
Requires-Dist: cryptography>=45.0.6
Requires-Dist: leb128>=1.0.8
Requires-Dist: protobuf>=6.32.1
Requires-Dist: pydantic<2
Requires-Dist: python-dateutil>=2.8.2
Requires-Dist: requests>=2.32.4
Requires-Dist: semver>=3.0.4
Requires-Dist: urllib3>=1.25.3
Requires-Dist: validators>=0.35.0
Requires-Python: >=3.10
Project-URL: Repository, https://github.com/xelato/wasm-action
